{
	"inputs" : 
	[
		{
			"path" : "CMakeLists.txt"
		},
		{
			"isGenerated" : true,
			"path" : "cmake-build-debug/CMakeFiles/3.24.2/CMakeSystem.cmake"
		},
		{
			"isCMake" : true,
			"isExternal" : true,
			"path" : "D:/JetBrains/apps/CLion/ch-0/223.8214.51/bin/cmake/win/share/cmake-3.24/Modules/CMakeSystemSpecificInitialize.cmake"
		},
		{
			"isGenerated" : true,
			"path" : "cmake-build-debug/CMakeFiles/3.24.2/CMakeCCompiler.cmake"
		},
		{
			"isCMake" : true,
			"isExternal" : true,
			"path" : "D:/JetBrains/apps/CLion/ch-0/223.8214.51/bin/cmake/win/share/cmake-3.24/Modules/CMakeSystemSpecificInformation.cmake"
		},
		{
			"isCMake" : true,
			"isExternal" : true,
			"path" : "D:/JetBrains/apps/CLion/ch-0/223.8214.51/bin/cmake/win/share/cmake-3.24/Modules/CMakeGenericSystem.cmake"
		},
		{
			"isCMake" : true,
			"isExternal" : true,
			"path" : "D:/JetBrains/apps/CLion/ch-0/223.8214.51/bin/cmake/win/share/cmake-3.24/Modules/CMakeInitializeConfigs.cmake"
		},
		{
			"isCMake" : true,
			"isExternal" : true,
			"path" : "D:/JetBrains/apps/CLion/ch-0/223.8214.51/bin/cmake/win/share/cmake-3.24/Modules/Platform/Windows.cmake"
		},
		{
			"isCMake" : true,
			"isExternal" : true,
			"path" : "D:/JetBrains/apps/CLion/ch-0/223.8214.51/bin/cmake/win/share/cmake-3.24/Modules/Platform/WindowsPaths.cmake"
		},
		{
			"isCMake" : true,
			"isExternal" : true,
			"path" : "D:/JetBrains/apps/CLion/ch-0/223.8214.51/bin/cmake/win/share/cmake-3.24/Modules/CMakeCInformation.cmake"
		},
		{
			"isCMake" : true,
			"isExternal" : true,
			"path" : "D:/JetBrains/apps/CLion/ch-0/223.8214.51/bin/cmake/win/share/cmake-3.24/Modules/CMakeLanguageInformation.cmake"
		},
		{
			"isCMake" : true,
			"isExternal" : true,
			"path" : "D:/JetBrains/apps/CLion/ch-0/223.8214.51/bin/cmake/win/share/cmake-3.24/Modules/Compiler/GNU-C.cmake"
		},
		{
			"isCMake" : true,
			"isExternal" : true,
			"path" : "D:/JetBrains/apps/CLion/ch-0/223.8214.51/bin/cmake/win/share/cmake-3.24/Modules/Compiler/GNU.cmake"
		},
		{
			"isCMake" : true,
			"isExternal" : true,
			"path" : "D:/JetBrains/apps/CLion/ch-0/223.8214.51/bin/cmake/win/share/cmake-3.24/Modules/Compiler/CMakeCommonCompilerMacros.cmake"
		},
		{
			"isCMake" : true,
			"isExternal" : true,
			"path" : "D:/JetBrains/apps/CLion/ch-0/223.8214.51/bin/cmake/win/share/cmake-3.24/Modules/Platform/Windows-GNU-C.cmake"
		},
		{
			"isCMake" : true,
			"isExternal" : true,
			"path" : "D:/JetBrains/apps/CLion/ch-0/223.8214.51/bin/cmake/win/share/cmake-3.24/Modules/Platform/Windows-GNU.cmake"
		},
		{
			"isGenerated" : true,
			"path" : "cmake-build-debug/CMakeFiles/3.24.2/CMakeRCCompiler.cmake"
		},
		{
			"isCMake" : true,
			"isExternal" : true,
			"path" : "D:/JetBrains/apps/CLion/ch-0/223.8214.51/bin/cmake/win/share/cmake-3.24/Modules/CMakeRCInformation.cmake"
		},
		{
			"isCMake" : true,
			"isExternal" : true,
			"path" : "D:/JetBrains/apps/CLion/ch-0/223.8214.51/bin/cmake/win/share/cmake-3.24/Modules/Platform/Windows-windres.cmake"
		},
		{
			"isCMake" : true,
			"isExternal" : true,
			"path" : "D:/JetBrains/apps/CLion/ch-0/223.8214.51/bin/cmake/win/share/cmake-3.24/Modules/Platform/Windows-GNU-C-ABI.cmake"
		},
		{
			"isCMake" : true,
			"isExternal" : true,
			"path" : "D:/JetBrains/apps/CLion/ch-0/223.8214.51/bin/cmake/win/share/cmake-3.24/Modules/CMakeCommonLanguageInclude.cmake"
		},
		{
			"path" : "data_structure/CMakeLists.txt"
		},
		{
			"path" : "data_structure/list/CMakeLists.txt"
		},
		{
			"path" : "tests/CMakeLists.txt"
		},
		{
			"isCMake" : true,
			"isExternal" : true,
			"path" : "D:/JetBrains/apps/CLion/ch-0/223.8214.51/bin/cmake/win/share/cmake-3.24/Modules/CTest.cmake"
		},
		{
			"isCMake" : true,
			"isExternal" : true,
			"path" : "D:/JetBrains/apps/CLion/ch-0/223.8214.51/bin/cmake/win/share/cmake-3.24/Modules/CTestUseLaunchers.cmake"
		},
		{
			"isCMake" : true,
			"isExternal" : true,
			"path" : "D:/JetBrains/apps/CLion/ch-0/223.8214.51/bin/cmake/win/share/cmake-3.24/Modules/CTestTargets.cmake"
		},
		{
			"isCMake" : true,
			"isExternal" : true,
			"path" : "D:/JetBrains/apps/CLion/ch-0/223.8214.51/bin/cmake/win/share/cmake-3.24/Modules/DartConfiguration.tcl.in"
		},
		{
			"path" : "third_party/unity/CMakeLists.txt"
		},
		{
			"isCMake" : true,
			"isExternal" : true,
			"path" : "D:/JetBrains/apps/CLion/ch-0/223.8214.51/bin/cmake/win/share/cmake-3.24/Modules/GNUInstallDirs.cmake"
		},
		{
			"isCMake" : true,
			"isExternal" : true,
			"path" : "D:/JetBrains/apps/CLion/ch-0/223.8214.51/bin/cmake/win/share/cmake-3.24/Modules/CMakePackageConfigHelpers.cmake"
		},
		{
			"isCMake" : true,
			"isExternal" : true,
			"path" : "D:/JetBrains/apps/CLion/ch-0/223.8214.51/bin/cmake/win/share/cmake-3.24/Modules/WriteBasicConfigVersionFile.cmake"
		},
		{
			"isCMake" : true,
			"isExternal" : true,
			"path" : "D:/JetBrains/apps/CLion/ch-0/223.8214.51/bin/cmake/win/share/cmake-3.24/Modules/BasicConfigVersion-SameMajorVersion.cmake.in"
		}
	],
	"kind" : "cmakeFiles",
	"paths" : 
	{
		"build" : "E:/Src/c-algorithm/cmake-build-debug",
		"source" : "E:/Src/c-algorithm"
	},
	"version" : 
	{
		"major" : 1,
		"minor" : 0
	}
}
